[
  {
    "id": 1,
    "name": "bwaSplitAWSPython",
    "functionType_id": 6,
    "algorithm": null,
    "implementationFilePath": null,
    "provider": 1,
    "language_id": 5,
    "avgRTT": 5082.469326937075,
    "avgCost": 0.00008694098332801215,
    "successRate": 0.9936037214711441,
    "computationWork": null,
    "memoryWork": null,
    "ioWork": null,
    "invocations": 13758
  },
  {
    "id": 2,
    "name": "bwaIndexAWSPython",
    "functionType_id": 7,
    "algorithm": null,
    "implementationFilePath": null,
    "provider": 1,
    "language_id": 5,
    "avgRTT": 7154.592271727171,
    "avgCost": 0.00012230528564756036,
    "successRate": 1,
    "computationWork": null,
    "memoryWork": null,
    "ioWork": null,
    "invocations": 14544
  },
  {
    "id": 3,
    "name": "bwaAlnR1AWSPython",
    "functionType_id": 8,
    "algorithm": null,
    "implementationFilePath": null,
    "provider": 1,
    "language_id": 5,
    "avgRTT": 15131.234540971174,
    "avgCost": 0.00025844025264537996,
    "successRate": 1,
    "computationWork": null,
    "memoryWork": null,
    "ioWork": null,
    "invocations": 10544
  },
  {
    "id": 4,
    "name": "bwaAlnR2AWSPython",
    "functionType_id": 9,
    "algorithm": null,
    "implementationFilePath": null,
    "provider": 1,
    "language_id": 5,
    "avgRTT": 20194.60318664645,
    "avgCost": 0.00034485525036122234,
    "successRate": 1,
    "computationWork": null,
    "memoryWork": null,
    "ioWork": null,
    "invocations": 10544
  },
  {
    "id": 5,
    "name": "bwaSampeAWSPython",
    "functionType_id": 10,
    "algorithm": null,
    "implementationFilePath": null,
    "provider": 1,
    "language_id": 5,
    "avgRTT": 11756.079002276154,
    "avgCost": 0.00020083748291301,
    "successRate": 1,
    "computationWork": null,
    "memoryWork": null,
    "ioWork": null,
    "invocations": 10544
  },
  {
    "id": 6,
    "name": "bwaMergeAWSPython",
    "functionType_id": 11,
    "algorithm": null,
    "implementationFilePath": null,
    "provider": 1,
    "language_id": 5,
    "avgRTT": 17776.584158415833,
    "avgCost": 0.00030358764307770303,
    "successRate": 1,
    "computationWork": null,
    "memoryWork": null,
    "ioWork": null,
    "invocations": 202
  },
  {
    "id": 7,
    "name": "bwaSortAWSPython",
    "functionType_id": 12,
    "algorithm": null,
    "implementationFilePath": null,
    "provider": 1,
    "language_id": 5,
    "avgRTT": 14684.272277227723,
    "avgCost": 0.00025081208142118067,
    "successRate": 1,
    "computationWork": null,
    "memoryWork": null,
    "ioWork": null,
    "invocations": 202
  },
  {
    "id": 11,
    "name": "bwaSplitIBMPython",
    "functionType_id": 6,
    "algorithm": null,
    "implementationFilePath": null,
    "provider": 2,
    "language_id": 5,
    "avgRTT": null,
    "avgCost": null,
    "successRate": null,
    "computationWork": null,
    "memoryWork": null,
    "ioWork": null,
    "invocations": 0
  },
  {
    "id": 12,
    "name": "bwaIndexIBMPython",
    "functionType_id": 7,
    "algorithm": null,
    "implementationFilePath": null,
    "provider": 2,
    "language_id": 5,
    "avgRTT": null,
    "avgCost": null,
    "successRate": null,
    "computationWork": null,
    "memoryWork": null,
    "ioWork": null,
    "invocations": 0
  },
  {
    "id": 13,
    "name": "bwaAlnR1IBMPython",
    "functionType_id": 8,
    "algorithm": null,
    "implementationFilePath": null,
    "provider": 2,
    "language_id": 5,
    "avgRTT": null,
    "avgCost": null,
    "successRate": null,
    "computationWork": null,
    "memoryWork": null,
    "ioWork": null,
    "invocations": 0
  },
  {
    "id": 14,
    "name": "bwaAlnR2IBMPython",
    "functionType_id": 9,
    "algorithm": null,
    "implementationFilePath": null,
    "provider": 2,
    "language_id": 5,
    "avgRTT": null,
    "avgCost": null,
    "successRate": null,
    "computationWork": null,
    "memoryWork": null,
    "ioWork": null,
    "invocations": 0
  },
  {
    "id": 15,
    "name": "bwaSampeIBMPython",
    "functionType_id": 10,
    "algorithm": null,
    "implementationFilePath": null,
    "provider": 2,
    "language_id": 5,
    "avgRTT": null,
    "avgCost": null,
    "successRate": null,
    "computationWork": null,
    "memoryWork": null,
    "ioWork": null,
    "invocations": 0
  },
  {
    "id": 16,
    "name": "bwaMergeIBMPython",
    "functionType_id": 11,
    "algorithm": null,
    "implementationFilePath": null,
    "provider": 2,
    "language_id": 5,
    "avgRTT": null,
    "avgCost": null,
    "successRate": null,
    "computationWork": null,
    "memoryWork": null,
    "ioWork": null,
    "invocations": 0
  },
  {
    "id": 17,
    "name": "bwaSortIBMPython",
    "functionType_id": 12,
    "algorithm": null,
    "implementationFilePath": null,
    "provider": 2,
    "language_id": 5,
    "avgRTT": null,
    "avgCost": null,
    "successRate": null,
    "computationWork": null,
    "memoryWork": null,
    "ioWork": null,
    "invocations": 0
  },
  {
    "id": 19,
    "name": "bwaSplitAWSPythonDPS",
    "functionType_id": 6,
    "algorithm": null,
    "implementationFilePath": "/home/sasko/Documents/Papers/2021/xAFCLSched/saaf_support_working/bwasplit1024SA.zip",
    "provider": 1,
    "language_id": 5,
    "avgRTT": 9829.67349472378,
    "avgCost": 0.00016796009649614138,
    "successRate": 0.9180633147113594,
    "computationWork": null,
    "memoryWork": null,
    "ioWork": null,
    "invocations": 1611
  },
  {
    "id": 20,
    "name": "bwaIndexAWSPythonDPS",
    "functionType_id": 7,
    "algorithm": null,
    "implementationFilePath": "/home/sasko/Documents/Papers/2021/xAFCLSched/saaf_support_working/bwaIndex1024SA.zip",
    "provider": 1,
    "language_id": 5,
    "avgRTT": 10398.900826446288,
    "avgCost": 0.00017767492905383154,
    "successRate": 1,
    "computationWork": null,
    "memoryWork": null,
    "ioWork": null,
    "invocations": 605
  },
  {
    "id": 21,
    "name": "bwaAlnR1AWSPythonDPS",
    "functionType_id": 8,
    "algorithm": null,
    "implementationFilePath": "/home/sasko/Documents/Papers/2021/xAFCLSched/saaf_support_working/bwaAln1024SA.zip",
    "provider": 1,
    "language_id": 5,
    "avgRTT": 20286.768595041347,
    "avgCost": 0.00034642820981040665,
    "successRate": 1,
    "computationWork": null,
    "memoryWork": null,
    "ioWork": null,
    "invocations": 605
  },
  {
    "id": 22,
    "name": "bwaAlnR2AWSPythonDPS",
    "functionType_id": 9,
    "algorithm": null,
    "implementationFilePath": "/home/sasko/Documents/Papers/2021/xAFCLSched/saaf_support_working/bwaAln21024SA.zip",
    "provider": 1,
    "language_id": 5,
    "avgRTT": 25189.181818181827,
    "avgCost": 0.00043009622948770904,
    "successRate": 1,
    "computationWork": null,
    "memoryWork": null,
    "ioWork": null,
    "invocations": 605
  },
  {
    "id": 23,
    "name": "bwaSampeAWSPythonDPS",
    "functionType_id": 10,
    "algorithm": null,
    "implementationFilePath": "/home/sasko/Documents/Papers/2021/xAFCLSched/saaf_support_working/bwaSampe1024SA.zip",
    "provider": 1,
    "language_id": 5,
    "avgRTT": 19467.26446280993,
    "avgCost": 0.00033244197798124964,
    "successRate": 0.9338842975206612,
    "computationWork": null,
    "memoryWork": null,
    "ioWork": null,
    "invocations": 605
  },
  {
    "id": 24,
    "name": "bwaMergeAWSPythonDPS",
    "functionType_id": 11,
    "algorithm": null,
    "implementationFilePath": "/home/sasko/Documents/Papers/2021/xAFCLSched/saaf_support_working/bwaMerge1024SA.zip",
    "provider": 1,
    "language_id": 5,
    "avgRTT": 22915.888888888894,
    "avgCost": 0.00039129861923271094,
    "successRate": 0.9629629629629629,
    "computationWork": null,
    "memoryWork": null,
    "ioWork": null,
    "invocations": 135
  },
  {
    "id": 25,
    "name": "bwaSortAWSPythonDPS",
    "functionType_id": 12,
    "algorithm": null,
    "implementationFilePath": "/home/sasko/Documents/Papers/2021/xAFCLSched/saaf_support_working/bwaSort1024SA.zip",
    "provider": 1,
    "language_id": 5,
    "avgRTT": 20297.84615384615,
    "avgCost": 0.000346617267192123,
    "successRate": 1,
    "computationWork": null,
    "memoryWork": null,
    "ioWork": null,
    "invocations": 130
  },
  {
    "id": 26,
    "name": "splitIBMPythonDPS",
    "functionType_id": 6,
    "algorithm": null,
    "implementationFilePath": "/home/sasko/Documents/Papers/2021/xAFCLSched/saaf_support_working/bwasplit1024SA.zip",
    "provider": 2,
    "language_id": 5,
    "avgRTT": 4634.008928571419,
    "avgCost": 0.00008239221942857148,
    "successRate": 1,
    "computationWork": null,
    "memoryWork": null,
    "ioWork": null,
    "invocations": 560
  },
  {
    "id": 27,
    "name": "bwaIndexIBMPythonDPS",
    "functionType_id": 7,
    "algorithm": null,
    "implementationFilePath": null,
    "provider": 2,
    "language_id": 5,
    "avgRTT": 7853.991071428572,
    "avgCost": 0.00013844566857142867,
    "successRate": 1,
    "computationWork": null,
    "memoryWork": null,
    "ioWork": null,
    "invocations": 560
  },
  {
    "id": 28,
    "name": "bwaAlnR1IBMPythonDPS",
    "functionType_id": 8,
    "algorithm": null,
    "implementationFilePath": null,
    "provider": 2,
    "language_id": 5,
    "avgRTT": 22173.54464285714,
    "avgCost": 0.0003877204571428574,
    "successRate": 1,
    "computationWork": null,
    "memoryWork": null,
    "ioWork": null,
    "invocations": 560
  },
  {
    "id": 29,
    "name": "bwaAlnR2IBMPythonDPS",
    "functionType_id": 9,
    "algorithm": null,
    "implementationFilePath": null,
    "provider": 2,
    "language_id": 5,
    "avgRTT": 33110.20535714282,
    "avgCost": 0.0005781058468571426,
    "successRate": 1,
    "computationWork": null,
    "memoryWork": null,
    "ioWork": null,
    "invocations": 560
  },
  {
    "id": 30,
    "name": "bwaSampeIBMPythonDPS",
    "functionType_id": 10,
    "algorithm": null,
    "implementationFilePath": null,
    "provider": 2,
    "language_id": 5,
    "avgRTT": 17703.294642857145,
    "avgCost": 0.00030990234514285703,
    "successRate": 1,
    "computationWork": null,
    "memoryWork": null,
    "ioWork": null,
    "invocations": 560
  },
  {
    "id": 31,
    "name": "bwaMergeIBMPythonDPS",
    "functionType_id": 11,
    "algorithm": null,
    "implementationFilePath": null,
    "provider": 2,
    "language_id": 5,
    "avgRTT": 14247.32142857143,
    "avgCost": 0.0002497407634285718,
    "successRate": 1,
    "computationWork": null,
    "memoryWork": null,
    "ioWork": null,
    "invocations": 140
  },
  {
    "id": 32,
    "name": "bwaSortIBMPythonDPS",
    "functionType_id": 12,
    "algorithm": null,
    "implementationFilePath": null,
    "provider": 2,
    "language_id": 5,
    "avgRTT": 13021.392857142857,
    "avgCost": 0.00022839979885714285,
    "successRate": 1,
    "computationWork": null,
    "memoryWork": null,
    "ioWork": null,
    "invocations": 140
  },
  {
    "id": 33,
    "name": "noopAWS1Python",
    "functionType_id": 24,
    "algorithm": null,
    "implementationFilePath": null,
    "provider": 1,
    "language_id": 5,
    "avgRTT": 924.4458259325045,
    "avgCost": 0.000002172155039624864,
    "successRate": 1,
    "computationWork": null,
    "memoryWork": null,
    "ioWork": null,
    "invocations": 1126
  },
  {
    "id": 34,
    "name": "noopAWS2Python",
    "functionType_id": 25,
    "algorithm": null,
    "implementationFilePath": null,
    "provider": 1,
    "language_id": 5,
    "avgRTT": 653.5017761989341,
    "avgCost": 0.0000015941399108319708,
    "successRate": 1,
    "computationWork": null,
    "memoryWork": null,
    "ioWork": null,
    "invocations": 1126
  },
  {
    "id": 35,
    "name": "noopGoogle1Python",
    "functionType_id": 26,
    "algorithm": null,
    "implementationFilePath": null,
    "provider": 3,
    "language_id": 5,
    "avgRTT": 581.0875000000004,
    "avgCost": 0.000001977802999999999,
    "successRate": 1,
    "computationWork": null,
    "memoryWork": null,
    "ioWork": null,
    "invocations": 400
  },
  {
    "id": 36,
    "name": "noopGoogle2Python",
    "functionType_id": 27,
    "algorithm": null,
    "implementationFilePath": null,
    "provider": 3,
    "language_id": 5,
    "avgRTT": 305.31250000000006,
    "avgCost": 0.0000013380049999999988,
    "successRate": 1,
    "computationWork": null,
    "memoryWork": null,
    "ioWork": null,
    "invocations": 400
  },
  {
    "id": 37,
    "name": "noopIBM1Python",
    "functionType_id": 28,
    "algorithm": null,
    "implementationFilePath": null,
    "provider": 2,
    "language_id": 5,
    "avgRTT": null,
    "avgCost": null,
    "successRate": null,
    "computationWork": null,
    "memoryWork": null,
    "ioWork": null,
    "invocations": 0
  },
  {
    "id": 38,
    "name": "noopIBM2Python",
    "functionType_id": 29,
    "algorithm": null,
    "implementationFilePath": null,
    "provider": 2,
    "language_id": 5,
    "avgRTT": null,
    "avgCost": null,
    "successRate": null,
    "computationWork": null,
    "memoryWork": null,
    "ioWork": null,
    "invocations": 0
  },
  {
    "id": 39,
    "name": "averagePi_AWS",
    "functionType_id": 30,
    "algorithm": null,
    "implementationFilePath": "/home/antoane/master/afcl_sched/src/python/AWS/averagePi.zip",
    "provider": 1,
    "language_id": 6,
    "avgRTT": 1096.2056497175126,
    "avgCost": 0.0000025385767298748007,
    "successRate": 0.8892655367231639,
    "computationWork": null,
    "memoryWork": null,
    "ioWork": null,
    "invocations": 885
  },
  {
    "id": 40,
    "name": "monteCarlo_AWS",
    "functionType_id": 31,
    "algorithm": null,
    "implementationFilePath": "/home/antoane/master/afcl_sched/src/python/AWS/monteCarlo.zip",
    "provider": 1,
    "language_id": 6,
    "avgRTT": 19345.377930496903,
    "avgCost": 0.00004147022212533911,
    "successRate": 0.9948762002242043,
    "computationWork": null,
    "memoryWork": null,
    "ioWork": null,
    "invocations": 164136
  },
  {
    "id": 41,
    "name": "averagePi_IBM",
    "functionType_id": 30,
    "algorithm": null,
    "implementationFilePath": "/home/antoane/master/afcl_sched/src/python/IBM/averagePi.zip",
    "provider": 2,
    "language_id": 6,
    "avgRTT": 598.7959183673473,
    "avgCost": 0.0000015184039183673476,
    "successRate": 1,
    "computationWork": null,
    "memoryWork": null,
    "ioWork": null,
    "invocations": 196
  },
  {
    "id": 42,
    "name": "monteCarlo_IBM",
    "functionType_id": 31,
    "algorithm": null,
    "implementationFilePath": "/home/antoane/master/afcl_sched/src/python/IBM/monteCarlo.zip",
    "provider": 2,
    "language_id": 6,
    "avgRTT": 25112.958787878735,
    "avgCost": 0.0000548612223224241,
    "successRate": 0.9806060606060606,
    "computationWork": null,
    "memoryWork": null,
    "ioWork": null,
    "invocations": 5775
  },
  {
    "id": 43,
    "name": "averagePi_Google",
    "functionType_id": 30,
    "algorithm": null,
    "implementationFilePath": "/home/antoane/master/afcl_sched/src/python/Google/averagePi",
    "provider": 3,
    "language_id": 6,
    "avgRTT": 4907.925287356321,
    "avgCost": 0.000012016066666666675,
    "successRate": 1,
    "computationWork": null,
    "memoryWork": null,
    "ioWork": null,
    "invocations": 174
  },
  {
    "id": 44,
    "name": "monteCarlo_Google",
    "functionType_id": 31,
    "algorithm": null,
    "implementationFilePath": "/home/antoane/master/afcl_sched/src/python/Google/monteCarlo",
    "provider": 3,
    "language_id": 6,
    "avgRTT": 15777.286616161617,
    "avgCost": 0.00003723298494949501,
    "successRate": 1,
    "computationWork": null,
    "memoryWork": null,
    "ioWork": null,
    "invocations": 1584
  },
  {
    "id": 45,
    "name": "bwaSplitIBMPythonSaafSupportEU",
    "functionType_id": 6,
    "algorithm": null,
    "implementationFilePath": "/home/antoane/master/afcl_sched/src/python/IBM/00_split_eu.zip",
    "provider": 2,
    "language_id": 5,
    "avgRTT": 13138.249999999998,
    "avgCost": 0.0002304340480000001,
    "successRate": 1,
    "computationWork": null,
    "memoryWork": null,
    "ioWork": null,
    "invocations": 96
  },
  {
    "id": 46,
    "name": "bwaIndexIBMPythonSaafSupportEU",
    "functionType_id": 7,
    "algorithm": null,
    "implementationFilePath": "/home/antoane/master/afcl_sched/src/python/IBM/01_bwaIndex_eu.zip",
    "provider": 2,
    "language_id": 5,
    "avgRTT": 17221.479166666668,
    "avgCost": 0.00030151490133333345,
    "successRate": 1,
    "computationWork": null,
    "memoryWork": null,
    "ioWork": null,
    "invocations": 48
  },
  {
    "id": 47,
    "name": "bwaAlnR1IBMPythonSaafSupportEU",
    "functionType_id": 8,
    "algorithm": null,
    "implementationFilePath": "/home/antoane/master/afcl_sched/src/python/IBM/02_bwaAln_1_eu.zip",
    "provider": 2,
    "language_id": 5,
    "avgRTT": 27424.520833333332,
    "avgCost": 0.00047912945066666676,
    "successRate": 1,
    "computationWork": null,
    "memoryWork": null,
    "ioWork": null,
    "invocations": 96
  },
  {
    "id": 48,
    "name": "bwaAlnR2IBMPythonSaafSupportEU",
    "functionType_id": 9,
    "algorithm": null,
    "implementationFilePath": "/home/antoane/master/afcl_sched/src/python/IBM/02_bwaAln_2_eu.zip",
    "provider": 2,
    "language_id": 5,
    "avgRTT": 38488.29166666665,
    "avgCost": 0.0006717275733333335,
    "successRate": 1,
    "computationWork": null,
    "memoryWork": null,
    "ioWork": null,
    "invocations": 96
  },
  {
    "id": 49,
    "name": "bwaSampeIBMPythonSaafSupportEU",
    "functionType_id": 10,
    "algorithm": null,
    "implementationFilePath": "/home/antoane/master/afcl_sched/src/python/IBM/03_bwaSampe_eu.zip",
    "provider": 2,
    "language_id": 5,
    "avgRTT": 32627.104166666668,
    "avgCost": 0.0005696960213333334,
    "successRate": 1,
    "computationWork": null,
    "memoryWork": null,
    "ioWork": null,
    "invocations": 96
  },
  {
    "id": 50,
    "name": "bwaMergeIBMPythonSaafSupportEU",
    "functionType_id": 11,
    "algorithm": null,
    "implementationFilePath": "/home/antoane/master/afcl_sched/src/python/IBM/04_samtoolsMerge_eu.zip",
    "provider": 2,
    "language_id": 5,
    "avgRTT": 20744,
    "avgCost": 0.000362834944,
    "successRate": 1,
    "computationWork": null,
    "memoryWork": null,
    "ioWork": null,
    "invocations": 2
  },
  {
    "id": 51,
    "name": "bwaSortIBMPythonSaafSupportEU",
    "functionType_id": 12,
    "algorithm": null,
    "implementationFilePath": "/home/antoane/master/afcl_sched/src/python/IBM/05_samtoolsSort_eu.zip",
    "provider": 2,
    "language_id": 5,
    "avgRTT": 13655,
    "avgCost": 0.000239429632,
    "successRate": 1,
    "computationWork": null,
    "memoryWork": null,
    "ioWork": null,
    "invocations": 2
  },
  {
    "id": 52,
    "name": "bwaSplitIBMPythonSaafSupportUS",
    "functionType_id": 6,
    "algorithm": null,
    "implementationFilePath": "/home/antoane/master/afcl_sched/src/python/IBM/00_split_us.zip",
    "provider": 2,
    "language_id": 5,
    "avgRTT": 6468.400462962963,
    "avgCost": 0.0001143253072592592,
    "successRate": 1,
    "computationWork": null,
    "memoryWork": null,
    "ioWork": null,
    "invocations": 432
  },
  {
    "id": 53,
    "name": "bwaIndexIBMPythonSaafSupportUS",
    "functionType_id": 7,
    "algorithm": null,
    "implementationFilePath": "/home/antoane/master/afcl_sched/src/python/IBM/01_bwaIndex_us.zip",
    "provider": 2,
    "language_id": 5,
    "avgRTT": 10541.668981481473,
    "avgCost": 0.00018523276562962948,
    "successRate": 1,
    "computationWork": null,
    "memoryWork": null,
    "ioWork": null,
    "invocations": 432
  },
  {
    "id": 54,
    "name": "bwaAlnR1IBMPythonSaafSupportUS",
    "functionType_id": 8,
    "algorithm": null,
    "implementationFilePath": "/home/antoane/master/afcl_sched/src/python/IBM/02_bwaAln_1_us.zip",
    "provider": 2,
    "language_id": 5,
    "avgRTT": 26906.10648148148,
    "avgCost": 0.00047010489362963,
    "successRate": 1,
    "computationWork": null,
    "memoryWork": null,
    "ioWork": null,
    "invocations": 432
  },
  {
    "id": 55,
    "name": "bwaAlnR2IBMPythonSaafSupportUS",
    "functionType_id": 9,
    "algorithm": null,
    "implementationFilePath": "/home/antoane/master/afcl_sched/src/python/IBM/02_bwaAln_2_us.zip",
    "provider": 2,
    "language_id": 5,
    "avgRTT": 38494.87962962962,
    "avgCost": 0.0006718422565925926,
    "successRate": 0.8611111111111112,
    "computationWork": null,
    "memoryWork": null,
    "ioWork": null,
    "invocations": 432
  },
  {
    "id": 56,
    "name": "bwaSampeIBMPythonSaafSupportUS",
    "functionType_id": 10,
    "algorithm": null,
    "implementationFilePath": "/home/antoane/master/afcl_sched/src/python/IBM/03_bwaSampe_us.zip",
    "provider": 2,
    "language_id": 5,
    "avgRTT": 17864.870370370365,
    "avgCost": 0.0003127150554074071,
    "successRate": 0.8587962962962963,
    "computationWork": null,
    "memoryWork": null,
    "ioWork": null,
    "invocations": 432
  },
  {
    "id": 57,
    "name": "bwaMergeIBMPythonSaafSupportUS",
    "functionType_id": 11,
    "algorithm": null,
    "implementationFilePath": "/home/antoane/master/afcl_sched/src/python/IBM/04_samtoolsMerge_us.zip",
    "provider": 2,
    "language_id": 5,
    "avgRTT": 10566,
    "avgCost": 0.00018565632000000002,
    "successRate": 1,
    "computationWork": null,
    "memoryWork": null,
    "ioWork": null,
    "invocations": 9
  },
  {
    "id": 58,
    "name": "bwaSortIBMPythonSaafSupportUS",
    "functionType_id": 12,
    "algorithm": null,
    "implementationFilePath": "/home/antoane/master/afcl_sched/src/python/IBM/05_samtoolsSort_us.zip",
    "provider": 2,
    "language_id": 5,
    "avgRTT": 7888.888888888889,
    "avgCost": 0.00013905316977777776,
    "successRate": 1,
    "computationWork": null,
    "memoryWork": null,
    "ioWork": null,
    "invocations": 9
  },
  {
    "id": 59,
    "name": "bwaSplitIBMPythonSaafSupportAPAC",
    "functionType_id": 6,
    "algorithm": null,
    "implementationFilePath": "/home/antoane/master/afcl_sched/src/python/IBM/00_split_apac.zip",
    "provider": 2,
    "language_id": 5,
    "avgRTT": null,
    "avgCost": null,
    "successRate": null,
    "computationWork": null,
    "memoryWork": null,
    "ioWork": null,
    "invocations": 0
  },
  {
    "id": 60,
    "name": "bwaIndexIBMPythonSaafSupportAPAC",
    "functionType_id": 7,
    "algorithm": null,
    "implementationFilePath": "/home/antoane/master/afcl_sched/src/python/IBM/01_bwaIndex_apac.zip",
    "provider": 2,
    "language_id": 5,
    "avgRTT": null,
    "avgCost": null,
    "successRate": null,
    "computationWork": null,
    "memoryWork": null,
    "ioWork": null,
    "invocations": 0
  },
  {
    "id": 61,
    "name": "bwaAlnR1IBMPythonSaafSupportAPAC",
    "functionType_id": 8,
    "algorithm": null,
    "implementationFilePath": "/home/antoane/master/afcl_sched/src/python/IBM/02_bwaAln_1_apac.zip",
    "provider": 2,
    "language_id": 5,
    "avgRTT": null,
    "avgCost": null,
    "successRate": null,
    "computationWork": null,
    "memoryWork": null,
    "ioWork": null,
    "invocations": 0
  },
  {
    "id": 62,
    "name": "bwaAlnR2IBMPythonSaafSupportAPAC",
    "functionType_id": 9,
    "algorithm": null,
    "implementationFilePath": "/home/antoane/master/afcl_sched/src/python/IBM/02_bwaAln_2_apac.zip",
    "provider": 2,
    "language_id": 5,
    "avgRTT": null,
    "avgCost": null,
    "successRate": null,
    "computationWork": null,
    "memoryWork": null,
    "ioWork": null,
    "invocations": 0
  },
  {
    "id": 63,
    "name": "bwaSampeIBMPythonSaafSupportAPAC",
    "functionType_id": 10,
    "algorithm": null,
    "implementationFilePath": "/home/antoane/master/afcl_sched/src/python/IBM/03_bwaSampe_apac.zip",
    "provider": 2,
    "language_id": 5,
    "avgRTT": null,
    "avgCost": null,
    "successRate": null,
    "computationWork": null,
    "memoryWork": null,
    "ioWork": null,
    "invocations": 0
  },
  {
    "id": 64,
    "name": "bwaMergeIBMPythonSaafSupportAPAC",
    "functionType_id": 11,
    "algorithm": null,
    "implementationFilePath": "/home/antoane/master/afcl_sched/src/python/IBM/04_samtoolsMerge_apac.zip",
    "provider": 2,
    "language_id": 5,
    "avgRTT": null,
    "avgCost": null,
    "successRate": null,
    "computationWork": null,
    "memoryWork": null,
    "ioWork": null,
    "invocations": 0
  },
  {
    "id": 65,
    "name": "bwaSortIBMPythonSaafSupportAPAC",
    "functionType_id": 12,
    "algorithm": null,
    "implementationFilePath": "/home/antoane/master/afcl_sched/src/python/IBM/05_samtoolsSort_apac.zip",
    "provider": 2,
    "language_id": 5,
    "avgRTT": null,
    "avgCost": null,
    "successRate": null,
    "computationWork": null,
    "memoryWork": null,
    "ioWork": null,
    "invocations": 0
  }
]